README.txt
buildout.cfg
setup.py
src/iwm/__init__.py
src/iwm.recipe.i18n.egg-info/PKG-INFO
src/iwm.recipe.i18n.egg-info/SOURCES.txt
src/iwm.recipe.i18n.egg-info/dependency_links.txt
src/iwm.recipe.i18n.egg-info/entry_points.txt
src/iwm.recipe.i18n.egg-info/requires.txt
src/iwm.recipe.i18n.egg-info/top_level.txt
src/iwm/recipe/__init__.py
src/iwm/recipe/i18n/README.txt
src/iwm/recipe/i18n/__init__.py
src/iwm/recipe/i18n/ctl.py
src/iwm/recipe/i18n/tests.py
