Metadata-Version: 1.0
Name: iwm.recipe.i18n
Version: 0.0.1
Summary: ZC Buildout recipe for creating i18n utilities
Home-page: http://svn.kmrc.de/projects/devel/iwm.recipe.i18n
Author: Stefan Martin
Author-email: s.martin@iwm-kmrc.de
License: GPL
Keywords: zope3 bebop build i18n
Platform: UNKNOWN
